LICENSE
README.md
setup.cfg
setup.py
vnpy_tdengine/__init__.py
vnpy_tdengine/tdengine_database.py
vnpy_tdengine/test.py
vnpy_tdengine.egg-info/PKG-INFO
vnpy_tdengine.egg-info/SOURCES.txt
vnpy_tdengine.egg-info/dependency_links.txt
vnpy_tdengine.egg-info/not-zip-safe
vnpy_tdengine.egg-info/requires.txt
vnpy_tdengine.egg-info/top_level.txt