Metadata-Version: 2.1
Name: vnpy-tdengine
Version: 1.0.1
Summary: Tdengine database manager for VeighNa quant trading framework.
Home-page: https://github.com/flytrap/vnpy_tdengine
Author: flytrap
Author-email: hiddenstat@gmail.com
License: MIT
Keywords: quant,quantitative,investment,trading,algotrading,tdengine,taos
Platform: UNKNOWN
Classifier: Development Status :: 5 - Production/Stable
Classifier: Operating System :: OS Independent
Classifier: Programming Language :: Python :: 3
Classifier: Programming Language :: Python :: 3.7
Classifier: Programming Language :: Python :: 3.8
Classifier: Programming Language :: Python :: 3.9
Classifier: Programming Language :: Python :: 3.10
Classifier: Topic :: Office/Business :: Financial :: Investment
Classifier: Programming Language :: Python :: Implementation :: CPython
Classifier: License :: OSI Approved :: MIT License
Classifier: Natural Language :: Chinese (Simplified)
License-File: LICENSE
